cachka/__init__.py
cachka/constants.py
cachka/core.py
cachka/interface.py
cachka/rediscache.py
cachka/registry.py
cachka/sqlitecache.py
cachka/ttllrucache.py
cachka/utils.py
cachka-0.2.6.dist-info/METADATA
cachka-0.2.6.dist-info/WHEEL
cachka-0.2.6.dist-info/RECORD
