Metadata-Version: 2.4
Name: cachka
Version: 0.2.6
Summary: Enterprise-grade hybrid cache for Python
Project-URL: Homepage, https://github.com/ed4b816e/cachka
Project-URL: Repository, https://github.com/ed4b816e/cachka
Project-URL: Documentation, https://github.com/ed4b816e/cachka#readme
License: MIT
Classifier: Development Status :: 4 - Beta
Classifier: Intended Audience :: Developers
Classifier: License :: OSI Approved :: MIT License
Classifier: Programming Language :: Python :: 3
Classifier: Programming Language :: Python :: 3.9
Classifier: Programming Language :: Python :: 3.10
Classifier: Programming Language :: Python :: 3.11
Classifier: Programming Language :: Python :: 3.12
Classifier: Topic :: Software Development :: Libraries :: Python Modules
Classifier: Topic :: System :: Distributed Computing
Requires-Python: >=3.9
Requires-Dist: aiosqlite>=0.21.0
Requires-Dist: structlog>=23.2.0
Provides-Extra: dev
Requires-Dist: cryptography>=41.0.0; extra == 'dev'
Requires-Dist: mypy>=1.5.0; extra == 'dev'
Requires-Dist: opentelemetry-api>=1.20.0; extra == 'dev'
Requires-Dist: opentelemetry-sdk>=1.20.0; extra == 'dev'
Requires-Dist: pre-commit>=4.2.0; extra == 'dev'
Requires-Dist: prometheus-client>=0.19.0; extra == 'dev'
Requires-Dist: pytest-asyncio>=1.2.0; extra == 'dev'
Requires-Dist: pytest-timeout>=2.4.0; extra == 'dev'
Requires-Dist: pytest>=8.4.2; extra == 'dev'
Requires-Dist: ruff>=0.1.0; extra == 'dev'
Requires-Dist: testcontainers>=4.0.0; extra == 'dev'
Provides-Extra: encryption
Requires-Dist: cryptography>=41.0.0; extra == 'encryption'
Provides-Extra: full
Requires-Dist: cryptography>=41.0.0; extra == 'full'
Requires-Dist: opentelemetry-api>=1.20.0; extra == 'full'
Requires-Dist: opentelemetry-sdk>=1.20.0; extra == 'full'
Requires-Dist: prometheus-client>=0.19.0; extra == 'full'
Requires-Dist: redis>=5.0.0; extra == 'full'
Provides-Extra: prometheus
Requires-Dist: prometheus-client>=0.19.0; extra == 'prometheus'
Provides-Extra: redis
Requires-Dist: redis>=5.0.0; extra == 'redis'
Provides-Extra: tracing
Requires-Dist: opentelemetry-api>=1.20.0; extra == 'tracing'
Requires-Dist: opentelemetry-sdk>=1.20.0; extra == 'tracing'
